{
    "status": "Success",
    "reason": "",
    "Lgdrvmaster": [
        {
            "District_Code": null,
            "District_Name": null,
            "District_Name_Tel": null,
            "Mandal_Code": null,
            "Mandal_Name": null,
            "Mandal_Name_Tel": null,
            "Revenue_Code": "595916",
            "Revenue_Name": "ALATHUR (ఆలత్తూరు)",
            "Revenue_Name_Tel": "ఆలత్తూరు",
            "Captureby": null,
            "CreatedDate": null,
            "LastmodifedDate": null,
            "Isactive": null
        },
        {
            "District_Code": null,
            "District_Name": null,
            "District_Name_Tel": null,
            "Mandal_Code": null,
            "Mandal_Name": null,
            "Mandal_Name_Tel": null,
            "Revenue_Code": "595915",
            "Revenue_Name": "BHAVANISANKARAPURAM (భవానిశంకరపురం)",
            "Revenue_Name_Tel": "భవానిశంకరపురం",
            "Captureby": null,
            "CreatedDate": null,
            "LastmodifedDate": null,
            "Isactive": null
        },
        {
            "District_Code": null,
            "District_Name": null,
            "District_Name_Tel": null,
            "Mandal_Code": null,
            "Mandal_Name": null,
            "Mandal_Name_Tel": null,
            "Revenue_Code": "595923",
            "Revenue_Name": "CHELLAMAMBAPURAM (చెల్లమాంబాపురము)",
            "Revenue_Name_Tel": "చెల్లమాంబాపురము",
            "Captureby": null,
            "CreatedDate": null,
            "LastmodifedDate": null,
            "Isactive": null
        },
        {
            "District_Code": null,
            "District_Name": null,
            "District_Name_Tel": null,
            "Mandal_Code": null,
            "Mandal_Name": null,
            "Mandal_Name_Tel": null,
            "Revenue_Code": "595919",
            "Revenue_Name": "CHINNAYYAGUNTA (చిన్నగుంట)",
            "Revenue_Name_Tel": "చిన్నగుంట",
            "Captureby": null,
            "CreatedDate": null,
            "LastmodifedDate": null,
            "Isactive": null
        },
        {
            "District_Code": null,
            "District_Name": null,
            "District_Name_Tel": null,
            "Mandal_Code": null,
            "Mandal_Name": null,
            "Mandal_Name_Tel": null,
            "Revenue_Code": "595932",
            "Revenue_Name": "GAJULAPELLURE (గాజులపెల్లూరు)",
            "Revenue_Name_Tel": "గాజులపెల్లూరు",
            "Captureby": null,
            "CreatedDate": null,
            "LastmodifedDate": null,
            "Isactive": null
        },
        {
            "District_Code": null,
            "District_Name": null,
            "District_Name_Tel": null,
            "Mandal_Code": null,
            "Mandal_Name": null,
            "Mandal_Name_Tel": null,
            "Revenue_Code": "595937",
            "Revenue_Name": "KALLIVETTU (కల్లివెట్టు)",
            "Revenue_Name_Tel": "కల్లివెట్టు",
            "Captureby": null,
            "CreatedDate": null,
            "LastmodifedDate": null,
            "Isactive": null
        },
        {
            "District_Code": null,
            "District_Name": null,
            "District_Name_Tel": null,
            "Mandal_Code": null,
            "Mandal_Name": null,
            "Mandal_Name_Tel": null,
            "Revenue_Code": "595929",
            "Revenue_Name": "KANAMANAMBEDU (కనమనంబేడు)",
            "Revenue_Name_Tel": "కనమనంబేడు",
            "Captureby": null,
            "CreatedDate": null,
            "LastmodifedDate": null,
            "Isactive": null
        },
        {
            "District_Code": null,
            "District_Name": null,
            "District_Name_Tel": null,
            "Mandal_Code": null,
            "Mandal_Name": null,
            "Mandal_Name_Tel": null,
            "Revenue_Code": "595933",
            "Revenue_Name": "KANCHANAPUTTUR (కాంచనపుత్తూరు)",
            "Revenue_Name_Tel": "కాంచనపుత్తూరు",
            "Captureby": null,
            "CreatedDate": null,
            "LastmodifedDate": null,
            "Isactive": null
        },
        {
            "District_Code": null,
            "District_Name": null,
            "District_Name_Tel": null,
            "Mandal_Code": null,
            "Mandal_Name": null,
            "Mandal_Name_Tel": null,
            "Revenue_Code": "595927",
            "Revenue_Name": "KATURU (కాటూరు)",
            "Revenue_Name_Tel": "కాటూరు",
            "Captureby": null,
            "CreatedDate": null,
            "LastmodifedDate": null,
            "Isactive": null
        },
        {
            "District_Code": null,
            "District_Name": null,
            "District_Name_Tel": null,
            "Mandal_Code": null,
            "Mandal_Name": null,
            "Mandal_Name_Tel": null,
            "Revenue_Code": "595922",
            "Revenue_Name": "KOTHAPALEM (కొత్తపాళెం)",
            "Revenue_Name_Tel": "కొత్తపాళెం",
            "Captureby": null,
            "CreatedDate": null,
            "LastmodifedDate": null,
            "Isactive": null
        },
        {
            "District_Code": null,
            "District_Name": null,
            "District_Name_Tel": null,
            "Mandal_Code": null,
            "Mandal_Name": null,
            "Mandal_Name_Tel": null,
            "Revenue_Code": "595931",
            "Revenue_Name": "KUKKAMBAKAM (కుక్కంబాకం)",
            "Revenue_Name_Tel": "కుక్కంబాకం",
            "Captureby": null,
            "CreatedDate": null,
            "LastmodifedDate": null,
            "Isactive": null
        },
        {
            "District_Code": null,
            "District_Name": null,
            "District_Name_Tel": null,
            "Mandal_Code": null,
            "Mandal_Name": null,
            "Mandal_Name_Tel": null,
            "Revenue_Code": "595936",
            "Revenue_Name": "KUMARA VENKATAPURAM (కె.వి.పురము)",
            "Revenue_Name_Tel": "కె.వి.పురము",
            "Captureby": null,
            "CreatedDate": null,
            "LastmodifedDate": null,
            "Isactive": null
        },
        {
            "District_Code": null,
            "District_Name": null,
            "District_Name_Tel": null,
            "Mandal_Code": null,
            "Mandal_Name": null,
            "Mandal_Name_Tel": null,
            "Revenue_Code": "595930",
            "Revenue_Name": "NEERPAKOTA (నీర్పకోట)",
            "Revenue_Name_Tel": "నీర్పకోట",
            "Captureby": null,
            "CreatedDate": null,
            "LastmodifedDate": null,
            "Isactive": null
        },
        {
            "District_Code": null,
            "District_Name": null,
            "District_Name_Tel": null,
            "Mandal_Code": null,
            "Mandal_Name": null,
            "Mandal_Name_Tel": null,
            "Revenue_Code": "595935",
            "Revenue_Name": "NELAVOY (నెలవాయి)",
            "Revenue_Name_Tel": "నెలవాయి",
            "Captureby": null,
            "CreatedDate": null,
            "LastmodifedDate": null,
            "Isactive": null
        },
        {
            "District_Code": null,
            "District_Name": null,
            "District_Name_Tel": null,
            "Mandal_Code": null,
            "Mandal_Name": null,
            "Mandal_Name_Tel": null,
            "Revenue_Code": "595926",
            "Revenue_Name": "PALLAMALA (పల్లమాల)",
            "Revenue_Name_Tel": "పల్లమాల",
            "Captureby": null,
            "CreatedDate": null,
            "LastmodifedDate": null,
            "Isactive": null
        },
        {
            "District_Code": null,
            "District_Name": null,
            "District_Name_Tel": null,
            "Mandal_Code": null,
            "Mandal_Name": null,
            "Mandal_Name_Tel": null,
            "Revenue_Code": "595925",
            "Revenue_Name": "PARLAPALLE (పార్లపల్లి)",
            "Revenue_Name_Tel": "పార్లపల్లి",
            "Captureby": null,
            "CreatedDate": null,
            "LastmodifedDate": null,
            "Isactive": null
        },
        {
            "District_Code": null,
            "District_Name": null,
            "District_Name_Tel": null,
            "Mandal_Code": null,
            "Mandal_Name": null,
            "Mandal_Name_Tel": null,
            "Revenue_Code": "595920",
            "Revenue_Name": "PEDDAPALAVEDU (పెద్దపాలవేడు)",
            "Revenue_Name_Tel": "పెద్దపాలవేడు",
            "Captureby": null,
            "CreatedDate": null,
            "LastmodifedDate": null,
            "Isactive": null
        },
        {
            "District_Code": null,
            "District_Name": null,
            "District_Name_Tel": null,
            "Mandal_Code": null,
            "Mandal_Name": null,
            "Mandal_Name_Tel": null,
            "Revenue_Code": "595918",
            "Revenue_Name": "PUTTERI (పుత్తేరి)",
            "Revenue_Name_Tel": "పుత్తేరి",
            "Captureby": null,
            "CreatedDate": null,
            "LastmodifedDate": null,
            "Isactive": null
        },
        {
            "District_Code": null,
            "District_Name": null,
            "District_Name_Tel": null,
            "Mandal_Code": null,
            "Mandal_Name": null,
            "Mandal_Name_Tel": null,
            "Revenue_Code": "595938",
            "Revenue_Name": "TALARIVETTU (తలారివెట్టు)",
            "Revenue_Name_Tel": "తలారివెట్టు",
            "Captureby": null,
            "CreatedDate": null,
            "LastmodifedDate": null,
            "Isactive": null
        },
        {
            "District_Code": null,
            "District_Name": null,
            "District_Name_Tel": null,
            "Mandal_Code": null,
            "Mandal_Name": null,
            "Mandal_Name_Tel": null,
            "Revenue_Code": "595928",
            "Revenue_Name": "THANGELLAPURAM (తంగేళ్ళపురము)",
            "Revenue_Name_Tel": "తంగేళ్ళపురము",
            "Captureby": null,
            "CreatedDate": null,
            "LastmodifedDate": null,
            "Isactive": null
        },
        {
            "District_Code": null,
            "District_Name": null,
            "District_Name_Tel": null,
            "Mandal_Code": null,
            "Mandal_Name": null,
            "Mandal_Name_Tel": null,
            "Revenue_Code": "595917",
            "Revenue_Name": "THERRIPADU (తేరిపాడు)",
            "Revenue_Name_Tel": "తేరిపాడు",
            "Captureby": null,
            "CreatedDate": null,
            "LastmodifedDate": null,
            "Isactive": null
        },
        {
            "District_Code": null,
            "District_Name": null,
            "District_Name_Tel": null,
            "Mandal_Code": null,
            "Mandal_Name": null,
            "Mandal_Name_Tel": null,
            "Revenue_Code": "595924",
            "Revenue_Name": "THIMMABHUPALAPURAM (తిమ్మభూపాలపురము)",
            "Revenue_Name_Tel": "తిమ్మభూపాలపురము",
            "Captureby": null,
            "CreatedDate": null,
            "LastmodifedDate": null,
            "Isactive": null
        },
        {
            "District_Code": null,
            "District_Name": null,
            "District_Name_Tel": null,
            "Mandal_Code": null,
            "Mandal_Name": null,
            "Mandal_Name_Tel": null,
            "Revenue_Code": "595921",
            "Revenue_Name": "VIJAYAGOPALAPURAM (విజయగొపాలపురము)",
            "Revenue_Name_Tel": "విజయగొపాలపురము",
            "Captureby": null,
            "CreatedDate": null,
            "LastmodifedDate": null,
            "Isactive": null
        },
        {
            "District_Code": null,
            "District_Name": null,
            "District_Name_Tel": null,
            "Mandal_Code": null,
            "Mandal_Name": null,
            "Mandal_Name_Tel": null,
            "Revenue_Code": "595934",
            "Revenue_Name": "WEST WARATHUR (పద్మరావరత్తూరు)",
            "Revenue_Name_Tel": "పద్మరావరత్తూరు",
            "Captureby": null,
            "CreatedDate": null,
            "LastmodifedDate": null,
            "Isactive": null
        }
    ]
}