{
    "status": "Success",
    "reason": "",
    "Lgdrvmaster": [
        {
            "District_Code": null,
            "District_Name": null,
            "District_Name_Tel": null,
            "Mandal_Code": null,
            "Mandal_Name": null,
            "Mandal_Name_Tel": null,
            "Revenue_Code": "591471",
            "Revenue_Name": "A.KOTHA PALLI (కొత్తపల్లె)",
            "Revenue_Name_Tel": "కొత్తపల్లె",
            "Captureby": null,
            "CreatedDate": null,
            "LastmodifedDate": null,
            "Isactive": null
        },
        {
            "District_Code": null,
            "District_Name": null,
            "District_Name_Tel": null,
            "Mandal_Code": null,
            "Mandal_Name": null,
            "Mandal_Name_Tel": null,
            "Revenue_Code": "591472",
            "Revenue_Name": "AMBAVARAM (అంబవరం)",
            "Revenue_Name_Tel": "అంబవరం",
            "Captureby": null,
            "CreatedDate": null,
            "LastmodifedDate": null,
            "Isactive": null
        },
        {
            "District_Code": null,
            "District_Name": null,
            "District_Name_Tel": null,
            "Mandal_Code": null,
            "Mandal_Name": null,
            "Mandal_Name_Tel": null,
            "Revenue_Code": "591463",
            "Revenue_Name": "ANIKALA PALLI (అనికల్లపల్లి)",
            "Revenue_Name_Tel": "అనికల్లపల్లి",
            "Captureby": null,
            "CreatedDate": null,
            "LastmodifedDate": null,
            "Isactive": null
        },
        {
            "District_Code": null,
            "District_Name": null,
            "District_Name_Tel": null,
            "Mandal_Code": null,
            "Mandal_Name": null,
            "Mandal_Name_Tel": null,
            "Revenue_Code": "591447",
            "Revenue_Name": "ARIVEMULA (ఆరివేముల)",
            "Revenue_Name_Tel": "ఆరివేముల",
            "Captureby": null,
            "CreatedDate": null,
            "LastmodifedDate": null,
            "Isactive": null
        },
        {
            "District_Code": null,
            "District_Name": null,
            "District_Name_Tel": null,
            "Mandal_Code": null,
            "Mandal_Name": null,
            "Mandal_Name_Tel": null,
            "Revenue_Code": "591453",
            "Revenue_Name": "BODAVULA DINNE (బోడవులదిన్నె)",
            "Revenue_Name_Tel": "బోడవులదిన్నె",
            "Captureby": null,
            "CreatedDate": null,
            "LastmodifedDate": null,
            "Isactive": null
        },
        {
            "District_Code": null,
            "District_Name": null,
            "District_Name_Tel": null,
            "Mandal_Code": null,
            "Mandal_Name": null,
            "Mandal_Name_Tel": null,
            "Revenue_Code": "591451",
            "Revenue_Name": "BONTHA VARI PALLI (బొంతవారిపల్లె)",
            "Revenue_Name_Tel": "బొంతవారిపల్లె",
            "Captureby": null,
            "CreatedDate": null,
            "LastmodifedDate": null,
            "Isactive": null
        },
        {
            "District_Code": null,
            "District_Name": null,
            "District_Name_Tel": null,
            "Mandal_Code": null,
            "Mandal_Name": null,
            "Mandal_Name_Tel": null,
            "Revenue_Code": "591442",
            "Revenue_Name": "BOYA MADUGULA (బోయమడుగుల)",
            "Revenue_Name_Tel": "బోయమడుగుల",
            "Captureby": null,
            "CreatedDate": null,
            "LastmodifedDate": null,
            "Isactive": null
        },
        {
            "District_Code": null,
            "District_Name": null,
            "District_Name_Tel": null,
            "Mandal_Code": null,
            "Mandal_Name": null,
            "Mandal_Name_Tel": null,
            "Revenue_Code": "591457",
            "Revenue_Name": "CHANDRA SEKHARA PURA (చంద్రశేకరపురం)",
            "Revenue_Name_Tel": "చంద్రశేకరపురం",
            "Captureby": null,
            "CreatedDate": null,
            "LastmodifedDate": null,
            "Isactive": null
        },
        {
            "District_Code": null,
            "District_Name": null,
            "District_Name_Tel": null,
            "Mandal_Code": null,
            "Mandal_Name": null,
            "Mandal_Name_Tel": null,
            "Revenue_Code": "591468",
            "Revenue_Name": "CHENNAPANAYUNI PALLE (చిన్నపనాయునిపల్లె)",
            "Revenue_Name_Tel": "చిన్నపనాయునిపల్లె",
            "Captureby": null,
            "CreatedDate": null,
            "LastmodifedDate": null,
            "Isactive": null
        },
        {
            "District_Code": null,
            "District_Name": null,
            "District_Name_Tel": null,
            "Mandal_Code": null,
            "Mandal_Name": null,
            "Mandal_Name_Tel": null,
            "Revenue_Code": "591446",
            "Revenue_Name": "CHINTALA PALEM (చింతలపాలెం)",
            "Revenue_Name_Tel": "చింతలపాలెం",
            "Captureby": null,
            "CreatedDate": null,
            "LastmodifedDate": null,
            "Isactive": null
        },
        {
            "District_Code": null,
            "District_Name": null,
            "District_Name_Tel": null,
            "Mandal_Code": null,
            "Mandal_Name": null,
            "Mandal_Name_Tel": null,
            "Revenue_Code": "591460",
            "Revenue_Name": "CHINTHAPUDI (చింతపూడి)",
            "Revenue_Name_Tel": "చింతపూడి",
            "Captureby": null,
            "CreatedDate": null,
            "LastmodifedDate": null,
            "Isactive": null
        },
        {
            "District_Code": null,
            "District_Name": null,
            "District_Name_Tel": null,
            "Mandal_Code": null,
            "Mandal_Name": null,
            "Mandal_Name_Tel": null,
            "Revenue_Code": "591456",
            "Revenue_Name": "DARSI THIMMAKKA PALL (దర్శతిమ్మక్కపల్లె)",
            "Revenue_Name_Tel": "దర్శతిమ్మక్కపల్లె",
            "Captureby": null,
            "CreatedDate": null,
            "LastmodifedDate": null,
            "Isactive": null
        },
        {
            "District_Code": null,
            "District_Name": null,
            "District_Name_Tel": null,
            "Mandal_Code": null,
            "Mandal_Name": null,
            "Mandal_Name_Tel": null,
            "Revenue_Code": "591450",
            "Revenue_Name": "DARSIGUNTA PETA (దర్శగుంటపేట)",
            "Revenue_Name_Tel": "దర్శగుంటపేట",
            "Captureby": null,
            "CreatedDate": null,
            "LastmodifedDate": null,
            "Isactive": null
        },
        {
            "District_Code": null,
            "District_Name": null,
            "District_Name_Tel": null,
            "Mandal_Code": null,
            "Mandal_Name": null,
            "Mandal_Name_Tel": null,
            "Revenue_Code": "591438",
            "Revenue_Name": "DEVAKI MARRI (దేవకిమర్రి)",
            "Revenue_Name_Tel": "దేవకిమర్రి",
            "Captureby": null,
            "CreatedDate": null,
            "LastmodifedDate": null,
            "Isactive": null
        },
        {
            "District_Code": null,
            "District_Name": null,
            "District_Name_Tel": null,
            "Mandal_Code": null,
            "Mandal_Name": null,
            "Mandal_Name_Tel": null,
            "Revenue_Code": "591466",
            "Revenue_Name": "GUNTACHENNAM PALLI (గుంతచెన్నంపల్లె)",
            "Revenue_Name_Tel": "గుంతచెన్నంపల్లె",
            "Captureby": null,
            "CreatedDate": null,
            "LastmodifedDate": null,
            "Isactive": null
        },
        {
            "District_Code": null,
            "District_Name": null,
            "District_Name_Tel": null,
            "Mandal_Code": null,
            "Mandal_Name": null,
            "Mandal_Name_Tel": null,
            "Revenue_Code": "591475",
            "Revenue_Name": "KAMBHAM PADU (కంభంపాడు)",
            "Revenue_Name_Tel": "కంభంపాడు",
            "Captureby": null,
            "CreatedDate": null,
            "LastmodifedDate": null,
            "Isactive": null
        },
        {
            "District_Code": null,
            "District_Name": null,
            "District_Name_Tel": null,
            "Mandal_Code": null,
            "Mandal_Name": null,
            "Mandal_Name_Tel": null,
            "Revenue_Code": "591459",
            "Revenue_Name": "KOMATIGUNTA (కోమటిగుంట)",
            "Revenue_Name_Tel": "కోమటిగుంట",
            "Captureby": null,
            "CreatedDate": null,
            "LastmodifedDate": null,
            "Isactive": null
        },
        {
            "District_Code": null,
            "District_Name": null,
            "District_Name_Tel": null,
            "Mandal_Code": null,
            "Mandal_Name": null,
            "Mandal_Name_Tel": null,
            "Revenue_Code": "591454",
            "Revenue_Name": "KONDABOYINA PALLI (కొండబోయనపల్లె)",
            "Revenue_Name_Tel": "కొండబోయనపల్లె",
            "Captureby": null,
            "CreatedDate": null,
            "LastmodifedDate": null,
            "Isactive": null
        },
        {
            "District_Code": null,
            "District_Name": null,
            "District_Name_Tel": null,
            "Mandal_Code": null,
            "Mandal_Name": null,
            "Mandal_Name_Tel": null,
            "Revenue_Code": "591462",
            "Revenue_Name": "KOVILA MPADU (కోవిలంపాడు)",
            "Revenue_Name_Tel": "కోవిలంపాడు",
            "Captureby": null,
            "CreatedDate": null,
            "LastmodifedDate": null,
            "Isactive": null
        },
        {
            "District_Code": null,
            "District_Name": null,
            "District_Name_Tel": null,
            "Mandal_Code": null,
            "Mandal_Name": null,
            "Mandal_Name_Tel": null,
            "Revenue_Code": "591470",
            "Revenue_Name": "MALAMEEDI PALLE (మాలమీదిపల్లె)",
            "Revenue_Name_Tel": "మాలమీదిపల్లె",
            "Captureby": null,
            "CreatedDate": null,
            "LastmodifedDate": null,
            "Isactive": null
        },
        {
            "District_Code": null,
            "District_Name": null,
            "District_Name_Tel": null,
            "Mandal_Code": null,
            "Mandal_Name": null,
            "Mandal_Name_Tel": null,
            "Revenue_Code": "591452",
            "Revenue_Name": "MEDANULU VENGANA PAL (మోడనూలు వెంగనపల్లె)",
            "Revenue_Name_Tel": "మోడనూలు వెంగనపల్లె",
            "Captureby": null,
            "CreatedDate": null,
            "LastmodifedDate": null,
            "Isactive": null
        },
        {
            "District_Code": null,
            "District_Name": null,
            "District_Name_Tel": null,
            "Mandal_Code": null,
            "Mandal_Name": null,
            "Mandal_Name_Tel": null,
            "Revenue_Code": "591445",
            "Revenue_Name": "MUNDLAPADU (ముండ్లపాడు)",
            "Revenue_Name_Tel": "ముండ్లపాడు",
            "Captureby": null,
            "CreatedDate": null,
            "LastmodifedDate": null,
            "Isactive": null
        },
        {
            "District_Code": null,
            "District_Name": null,
            "District_Name_Tel": null,
            "Mandal_Code": null,
            "Mandal_Name": null,
            "Mandal_Name_Tel": null,
            "Revenue_Code": "591458",
            "Revenue_Name": "MUSUNOOR (మూసునూరు)",
            "Revenue_Name_Tel": "మూసునూరు",
            "Captureby": null,
            "CreatedDate": null,
            "LastmodifedDate": null,
            "Isactive": null
        },
        {
            "District_Code": null,
            "District_Name": null,
            "District_Name_Tel": null,
            "Mandal_Code": null,
            "Mandal_Name": null,
            "Mandal_Name_Tel": null,
            "Revenue_Code": "591461",
            "Revenue_Name": "NAGULAVARAM (నాగులవరం)",
            "Revenue_Name_Tel": "నాగులవరం",
            "Captureby": null,
            "CreatedDate": null,
            "LastmodifedDate": null,
            "Isactive": null
        },
        {
            "District_Code": null,
            "District_Name": null,
            "District_Name_Tel": null,
            "Mandal_Code": null,
            "Mandal_Name": null,
            "Mandal_Name_Tel": null,
            "Revenue_Code": "591474",
            "Revenue_Name": "NALAJANAM PADU (నలజనంపాడు)",
            "Revenue_Name_Tel": "నలజనంపాడు",
            "Captureby": null,
            "CreatedDate": null,
            "LastmodifedDate": null,
            "Isactive": null
        },
        {
            "District_Code": null,
            "District_Name": null,
            "District_Name_Tel": null,
            "Mandal_Code": null,
            "Mandal_Name": null,
            "Mandal_Name_Tel": null,
            "Revenue_Code": "591464",
            "Revenue_Name": "NALLAMADUGULA (నల్లమడుగుల)",
            "Revenue_Name_Tel": "నల్లమడుగుల",
            "Captureby": null,
            "CreatedDate": null,
            "LastmodifedDate": null,
            "Isactive": null
        },
        {
            "District_Code": null,
            "District_Name": null,
            "District_Name_Tel": null,
            "Mandal_Code": null,
            "Mandal_Name": null,
            "Mandal_Name_Tel": null,
            "Revenue_Code": "591444",
            "Revenue_Name": "PEDAGOGULAPALLI (పెదగోగులపల్లి)",
            "Revenue_Name_Tel": "పెదగోగులపల్లి",
            "Captureby": null,
            "CreatedDate": null,
            "LastmodifedDate": null,
            "Isactive": null
        },
        {
            "District_Code": null,
            "District_Name": null,
            "District_Name_Tel": null,
            "Mandal_Code": null,
            "Mandal_Name": null,
            "Mandal_Name_Tel": null,
            "Revenue_Code": "591473",
            "Revenue_Name": "PEDARAJU PALEM (పెదరాజుపాలెం)",
            "Revenue_Name_Tel": "పెదరాజుపాలెం",
            "Captureby": null,
            "CreatedDate": null,
            "LastmodifedDate": null,
            "Isactive": null
        },
        {
            "District_Code": null,
            "District_Name": null,
            "District_Name_Tel": null,
            "Mandal_Code": null,
            "Mandal_Name": null,
            "Mandal_Name_Tel": null,
            "Revenue_Code": "591455",
            "Revenue_Name": "RANGANAYUNI PALLI (రంగనాయునిపల్లె)",
            "Revenue_Name_Tel": "రంగనాయునిపల్లె",
            "Captureby": null,
            "CreatedDate": null,
            "LastmodifedDate": null,
            "Isactive": null
        },
        {
            "District_Code": null,
            "District_Name": null,
            "District_Name_Tel": null,
            "Mandal_Code": null,
            "Mandal_Name": null,
            "Mandal_Name_Tel": null,
            "Revenue_Code": "591467",
            "Revenue_Name": "REGULA CHILAKA (రేగులచిలక)",
            "Revenue_Name_Tel": "రేగులచిలక",
            "Captureby": null,
            "CreatedDate": null,
            "LastmodifedDate": null,
            "Isactive": null
        },
        {
            "District_Code": null,
            "District_Name": null,
            "District_Name_Tel": null,
            "Mandal_Code": null,
            "Mandal_Name": null,
            "Mandal_Name_Tel": null,
            "Revenue_Code": "591440",
            "Revenue_Name": "TALANEELAMALA (తెలనీలమల)",
            "Revenue_Name_Tel": "తెలనీలమల",
            "Captureby": null,
            "CreatedDate": null,
            "LastmodifedDate": null,
            "Isactive": null
        },
        {
            "District_Code": null,
            "District_Name": null,
            "District_Name_Tel": null,
            "Mandal_Code": null,
            "Mandal_Name": null,
            "Mandal_Name_Tel": null,
            "Revenue_Code": "591449",
            "Revenue_Name": "THUMMAGUNTA (తుమ్మగుంట)",
            "Revenue_Name_Tel": "తుమ్మగుంట",
            "Captureby": null,
            "CreatedDate": null,
            "LastmodifedDate": null,
            "Isactive": null
        },
        {
            "District_Code": null,
            "District_Name": null,
            "District_Name_Tel": null,
            "Mandal_Code": null,
            "Mandal_Name": null,
            "Mandal_Name_Tel": null,
            "Revenue_Code": "591439",
            "Revenue_Name": "THUNGODU (తునుగోడు)",
            "Revenue_Name_Tel": "తునుగోడు",
            "Captureby": null,
            "CreatedDate": null,
            "LastmodifedDate": null,
            "Isactive": null
        },
        {
            "District_Code": null,
            "District_Name": null,
            "District_Name_Tel": null,
            "Mandal_Code": null,
            "Mandal_Name": null,
            "Mandal_Name_Tel": null,
            "Revenue_Code": "591465",
            "Revenue_Name": "UPPALAPADU (ఉప్పలపాడు)",
            "Revenue_Name_Tel": "ఉప్పలపాడు",
            "Captureby": null,
            "CreatedDate": null,
            "LastmodifedDate": null,
            "Isactive": null
        },
        {
            "District_Code": null,
            "District_Name": null,
            "District_Name_Tel": null,
            "Mandal_Code": null,
            "Mandal_Name": null,
            "Mandal_Name_Tel": null,
            "Revenue_Code": "591469",
            "Revenue_Name": "VATLA BAYALU (వట్ల బయలు)",
            "Revenue_Name_Tel": "వట్ల బయలు",
            "Captureby": null,
            "CreatedDate": null,
            "LastmodifedDate": null,
            "Isactive": null
        },
        {
            "District_Code": null,
            "District_Name": null,
            "District_Name_Tel": null,
            "Mandal_Code": null,
            "Mandal_Name": null,
            "Mandal_Name_Tel": null,
            "Revenue_Code": "591441",
            "Revenue_Name": "VENKATAYA CHERUVU (వెంకటాయచెరువు)",
            "Revenue_Name_Tel": "వెంకటాయచెరువు",
            "Captureby": null,
            "CreatedDate": null,
            "LastmodifedDate": null,
            "Isactive": null
        },
        {
            "District_Code": null,
            "District_Name": null,
            "District_Name_Tel": null,
            "Mandal_Code": null,
            "Mandal_Name": null,
            "Mandal_Name_Tel": null,
            "Revenue_Code": "591443",
            "Revenue_Name": "VIRANCHI PURAM (వీరనాంచిపురం)",
            "Revenue_Name_Tel": "వీరనాంచిపురం",
            "Captureby": null,
            "CreatedDate": null,
            "LastmodifedDate": null,
            "Isactive": null
        },
        {
            "District_Code": null,
            "District_Name": null,
            "District_Name_Tel": null,
            "Mandal_Code": null,
            "Mandal_Name": null,
            "Mandal_Name_Tel": null,
            "Revenue_Code": "591448",
            "Revenue_Name": "YEKUNAM PURAM (ఎకనంపురం)",
            "Revenue_Name_Tel": "ఎకనంపురం",
            "Captureby": null,
            "CreatedDate": null,
            "LastmodifedDate": null,
            "Isactive": null
        }
    ]
}